mininet/__init__.py
mininet/clean.py
mininet/cli.py
mininet/link.py
mininet/log.py
mininet/moduledeps.py
mininet/net.py
mininet/node.py
mininet/nodelib.py
mininet/term.py
mininet/topo.py
mininet/topolib.py
mininet/util.py
mininet/examples/__init__.py
mininet/examples/baresshd.py
mininet/examples/bind.py
mininet/examples/cluster.py
mininet/examples/clusterSanity.py
mininet/examples/clustercli.py
mininet/examples/clusterdemo.py
mininet/examples/clusterperf.py
mininet/examples/consoles.py
mininet/examples/controllers.py
mininet/examples/controllers2.py
mininet/examples/controlnet.py
mininet/examples/cpu.py
mininet/examples/emptynet.py
mininet/examples/hwintf.py
mininet/examples/intfoptions.py
mininet/examples/limit.py
mininet/examples/linearbandwidth.py
mininet/examples/linuxrouter.py
mininet/examples/miniedit.py
mininet/examples/mobility.py
mininet/examples/multilink.py
mininet/examples/multiping.py
mininet/examples/multipoll.py
mininet/examples/multitest.py
mininet/examples/nat.py
mininet/examples/natnet.py
mininet/examples/numberedports.py
mininet/examples/popen.py
mininet/examples/popenpoll.py
mininet/examples/scratchnet.py
mininet/examples/scratchnetuser.py
mininet/examples/simpleperf.py
mininet/examples/sshd.py
mininet/examples/tree1024.py
mininet/examples/treeping64.py
mininet/examples/vlanhost.py
mininet-2.3.0.dev6.data/scripts/mn
mininet-2.3.0.dev6.dist-info/LICENSE
mininet-2.3.0.dev6.dist-info/METADATA
mininet-2.3.0.dev6.dist-info/WHEEL
mininet-2.3.0.dev6.dist-info/top_level.txt
mininet-2.3.0.dev6.dist-info/RECORD
