Metadata-Version: 1.1
Name: mininet
Version: 2.3.0.dev6
Summary: Process-based OpenFlow emulator
Home-page: UNKNOWN
Author: Bob Lantz
Author-email: rlantz@cs.stanford.edu
License: BSD
Keywords: networking emulator protocol Internet OpenFlow SDN
Platform: UNKNOWN
Classifier: License :: OSI Approved :: BSD License
Classifier: Programming Language :: Python
Classifier: Development Status :: 5 - Production/Stable
Classifier: Intended Audience :: Developers
Classifier: Topic :: System :: Emulators
